Workbook
Name _Toc231161166: 'Table 21'!$A$1
Name _Toc231161169: 'Table 24'!$A$1
Name _Toc231161170: 'Table 25'!$A$1
Name _Toc231161172: 'Table 27'!$A$1
Name _Toc231161175: 'Table 30'!$A$1

Sheet site_model_risk
A1: run_type | B1: run_no | C1: site_name | D1: domain | E1: model | F1: weighted_risk_score | G1: unweighted_risk_score | H1: max_weighted_score | I1: hallucination_count | J1: validation_denominator | K1: indicator_count | L1: total_chunks | M1: successful_chunks | N1: malformed_chunks | O1: chunk_coverage | P1: weighted_risk_ratio | Q1: risk_tier | R1: hallucination_rate
A2: main | B2: 1 | C2: About You | D2: aboutyou.de | E2: CLAUDE | F2: 3 | G2: 1 | H2: 42 | I2: 0 | J2: 18 | K2: 18 | L2: 2 | M2: 2 | N2: 0 | O2: 1 | P2: 0.071428571 | Q2: Low Risk | R2: 0
A3: main | B3: 1 | C3: About You | D3: aboutyou.de | E3: GEMINI | F3: 3 | G3: 1 | H3: 42 | I3: 0 | J3: 18 | K3: 18 | L3: 2 | M3: 2 | N3: 0 | O3: 1 | P3: 0.071428571 | Q3: Low Risk | R3: 0
A4: main | B4: 1 | C4: About You | D4: aboutyou.de | E4: GPT | F4: 8 | G4: 3 | H4: 42 | I4: 1 | J4: 18 | K4: 18 | L4: 2 | M4: 2 | N4: 0 | O4: 1 | P4: 0.19047619 | Q4: Low Risk | R4: 0.055555556
A5: main | B5: 1 | C5: About You | D5: aboutyou.de | E5: LLAMA | F5: 3 | G5: 1 | H5: 39 | I5: 0 | J5: 16 | K5: 17 | L5: 2 | M5: 2 | N5: 0 | O5: 1 | P5: 0.076923077 | Q5: Low Risk | R5: 0
A6: main | B6: 1 | C6: Allegro | D6: allegro.pl | E6: CLAUDE | F6: 2 | G6: 1 | H6: 42 | I6: 0 | J6: 15 | K6: 18 | L6: 4 | M6: 4 | N6: 0 | O6: 1 | P6: 0.047619048 | Q6: Low Risk | R6: 0
A7: main | B7: 1 | C7: Allegro | D7: allegro.pl | E7: GEMINI | F7: 3 | G7: 1 | H7: 42 | I7: 0 | J7: 18 | K7: 18 | L7: 4 | M7: 4 | N7: 0 | O7: 1 | P7: 0.071428571 | Q7: Low Risk | R7: 0
A8: main | B8: 1 | C8: Allegro | D8: allegro.pl | E8: GPT | F8: 5 | G8: 2 | H8: 42 | I8: 1 | J8: 17 | K8: 18 | L8: 4 | M8: 4 | N8: 0 | O8: 1 | P8: 0.11904762 | Q8: Low Risk | R8: 0.058823529
A9: main | B9: 1 | C9: Allegro | D9: allegro.pl | E9: LLAMA | F9: 2 | G9: 1 | H9: 39 | I9: 0 | J9: 14 | K9: 17 | L9: 4 | M9: 4 | N9: 0 | O9: 1 | P9: 0.051282051 | Q9: Low Risk | R9: 0
A10: main | B10: 1 | C10: Amazon | D10: amazon.de | E10: CLAUDE | F10: 5 | G10: 2 | H10: 42 | I10: 0 | J10: 16 | K10: 18 | L10: 1 | M10: 1 | N10: 0 | O10: 1 | P10: 0.11904762 | Q10: Low Risk | R10: 0
A11: main | B11: 1 | C11: Amazon | D11: amazon.de | E11: GEMINI | F11: 8 | G11: 3 | H11: 42 | I11: 0 | J11: 18 | K11: 18 | L11: 1 | M11: 1 | N11: 0 | O11: 1 | P11: 0.19047619 | Q11: Low Risk | R11: 0
A12: main | B12: 1 | C12: Amazon | D12: amazon.de | E12: GPT | F12: 5 | G12: 2 | H12: 42 | I12: 0 | J12: 17 | K12: 18 | L12: 1 | M12: 1 | N12: 0 | O12: 1 | P12: 0.11904762 | Q12: Low Risk | R12: 0
A13: main | B13: 1 | C13: Amazon | D13: amazon.de | E13: LLAMA | F13: 0 | G13: 0 | H13: 39 | I13: 0 | J13: 15 | K13: 17 | L13: 1 | M13: 1 | N13: 0 | O13: 1 | P13: 0 | Q13: Low Risk | R13: 0
... A81: main | B81: 1 | C81: eMAG | D81: emag.ro | E81: LLAMA | F81: 2 | G81: 1 | H81: 39 | I81: 0 | J81: 14 | K81: 17 | L81: 2 | M81: 2 | N81: 0 | O81: 1 | P81: 0.051282051 | Q81: Low Risk | R81: 0

Sheet Table 21
A1: Table 21. Total Risk Flags by Model and Indicator Group
B2: GPT | C2: CLAUDE | D2: GEMINI | E2: LLAMA | F2: Total
A3: Validity of Consent (R01–R06) | B3: =SUMIFS(indicator_model!$G$2:$G$72,indicator_model!$E$2:$E$72,B$2,indicator_model!$C$2:$C$72,">=R01",indicator_model!$C$2:$C$72,"<=R06") -> 27 | C3: =SUMIFS(indicator_model!$G$2:$G$72,indicator_model!$E$2:$E$72,C$2,indicator_model!$C$2:$C$72,">=R01",indicator_model!$C$2:$C$72,"<=R06") -> 15 | D3: =SUMIFS(indicator_model!$G$2:$G$72,indicator_model!$E$2:$E$72,D$2,indicator_model!$C$2:$C$72,">=R01",indicator_model!$C$2:$C$72,"<=R06") -> 18 | E3: =SUMIFS(indicator_model!$G$2:$G$72,indicator_model!$E$2:$E$72,E$2,indicator_model!$C$2:$C$72,">=R01",indicator_model!$C$2:$C$72,"<=R06") -> 19 | F3: =SUM(B3:E3) -> 79
A4: Transparency (R07–R15, R18) | B4: =SUMIFS(indicator_model!$G$2:$G$72,indicator_model!$E$2:$E$72,B$2,indicator_model!$C$2:$C$72,">=R07",indicator_model!$C$2:$C$72,"<=R15")+SUMIFS(indicator_model!$G$2:$G$72,indicator_model!$E$2:$E$72,B$2,indicator_model!$C$2:$C$72,"R18") -> 17 | C4: =SUMIFS(indicator_model!$G$2:$G$72,indicator_model!$E$2:$E$72,C$2,indicator_model!$C$2:$C$72,">=R07",indicator_model!$C$2:$C$72,"<=R15")+SUMIFS(indicator_model!$G$2:$G$72,indicator_model!$E$2:$E$72,C$2,indicator_model!$C$2:$C$72,"R18") -> 4 | D4: =SUMIFS(indicator_model!$G$2:$G$72,indicator_model!$E$2:$E$72,D$2,indicator_model!$C$2:$C$72,">=R07",indicator_model!$C$2:$C$72,"<=R15")+SUMIFS(indicator_model!$G$2:$G$72,indicator_model!$E$2:$E$72,D$2,indicator_model!$C$2:$C$72,"R18") -> 6 | E4: =SUMIFS(indicator_model!$G$2:$G$72,indicator_model!$E$2:$E$72,E$2,indicator_model!$C$2:$C$72,">=R07",indicator_model!$C$2:$C$72,"<=R15")+SUMIFS(indicator_model!$G$2:$G$72,indicator_model!$E$2:$E$72,E$2,indicator_model!$C$2:$C$72,"R18") -> 0 | F4: =SUM(B4:E4) -> 27
A5: Accountability and Tech (R16–R17) | B5: =SUMIFS(indicator_model!$G$2:$G$72,indicator_model!$E$2:$E$72,B$2,indicator_model!$C$2:$C$72,">=R16",indicator_model!$C$2:$C$72,"<=R17") -> 11 | C5: =SUMIFS(indicator_model!$G$2:$G$72,indicator_model!$E$2:$E$72,C$2,indicator_model!$C$2:$C$72,">=R16",indicator_model!$C$2:$C$72,"<=R17") -> 18 | D5: =SUMIFS(indicator_model!$G$2:$G$72,indicator_model!$E$2:$E$72,D$2,indicator_model!$C$2:$C$72,">=R16",indicator_model!$C$2:$C$72,"<=R17") -> 15 | E5: =SUMIFS(indicator_model!$G$2:$G$72,indicator_model!$E$2:$E$72,E$2,indicator_model!$C$2:$C$72,">=R16",indicator_model!$C$2:$C$72,"<=R17") -> 0 | F5: =SUM(B5:E5) -> 44
A6: Total Risks Detected | B6: =SUM(B3:B5) -> 55 | C6: =SUM(C3:C5) -> 37 | D6: =SUM(D3:D5) -> 39 | E6: =SUM(E3:E5) -> 19 | F6: =SUM(F3:F5) -> 150

Sheet Table 22
A1: Table 22. Severity-Weighted Risk Scores by Site and Model
A2: Site | B2: CLAUDE | C2: GEMINI | D2: GPT | E2: LLAMA | F2: Range W | G2: Risk Tier
A3: About You | B3: {=SUMPRODUCT((site_model_risk!$C$2:$C$500=A3)*(site_model_risk!$E$2:$E$500=B$2)*site_model_risk!$F$2:$F$500)} -> 3 | C3: {=SUMPRODUCT((site_model_risk!$C$2:$C$500=$A3)*(site_model_risk!$E$2:$E$500=C$2)*site_model_risk!$F$2:$F$500)} -> 3 | D3: {=SUMPRODUCT((site_model_risk!$C$2:$C$500=$A3)*(site_model_risk!$E$2:$E$500=D$2)*site_model_risk!$F$2:$F$500)} -> 8 | E3: {=SUMPRODUCT((site_model_risk!$C$2:$C$500=$A3)*(site_model_risk!$E$2:$E$500=E$2)*site_model_risk!$F$2:$F$500)} -> 3 | F3: =MAX(B3:E3)-MIN(B3:E3) -> 5 | G3: =IF(MAX(B3:E3)>=30,"Critical",IF(MAX(B3:E3)>=20,"High Risk",IF(MAX(B3:E3)>=10,"Medium Risk","Low Risk"))) -> Low Risk
A4: Allegro | B4: {=SUMPRODUCT((site_model_risk!$C$2:$C$500=A4)*(site_model_risk!$E$2:$E$500=B$2)*site_model_risk!$F$2:$F$500)} -> 2 | C4: {=SUMPRODUCT((site_model_risk!$C$2:$C$500=$A4)*(site_model_risk!$E$2:$E$500=C$2)*site_model_risk!$F$2:$F$500)} -> 3 | D4: {=SUMPRODUCT((site_model_risk!$C$2:$C$500=$A4)*(site_model_risk!$E$2:$E$500=D$2)*site_model_risk!$F$2:$F$500)} -> 5 | E4: {=SUMPRODUCT((site_model_risk!$C$2:$C$500=$A4)*(site_model_risk!$E$2:$E$500=E$2)*site_model_risk!$F$2:$F$500)} -> 2 | F4: =MAX(B4:E4)-MIN(B4:E4) -> 3 | G4: =IF(MAX(B4:E4)>=30,"Critical",IF(MAX(B4:E4)>=20,"High Risk",IF(MAX(B4:E4)>=10,"Medium Risk","Low Risk"))) -> Low Risk
A5: Amazon | B5: {=SUMPRODUCT((site_model_risk!$C$2:$C$500=A5)*(site_model_risk!$E$2:$E$500=B$2)*site_model_risk!$F$2:$F$500)} -> 5 | C5: {=SUMPRODUCT((site_model_risk!$C$2:$C$500=$A5)*(site_model_risk!$E$2:$E$500=C$2)*site_model_risk!$F$2:$F$500)} -> 8 | D5: {=SUMPRODUCT((site_model_risk!$C$2:$C$500=$A5)*(site_model_risk!$E$2:$E$500=D$2)*site_model_risk!$F$2:$F$500)} -> 5 | E5: {=SUMPRODUCT((site_model_risk!$C$2:$C$500=$A5)*(site_model_risk!$E$2:$E$500=E$2)*site_model_risk!$F$2:$F$500)} -> 0 | F5: =MAX(B5:E5)-MIN(B5:E5) -> 8 | G5: =IF(MAX(B5:E5)>=30,"Critical",IF(MAX(B5:E5)>=20,"High Risk",IF(MAX(B5:E5)>=10,"Medium Risk","Low Risk"))) -> Low Risk
A6: Answear | B6: {=SUMPRODUCT((site_model_risk!$C$2:$C$500=A6)*(site_model_risk!$E$2:$E$500=B$2)*site_model_risk!$F$2:$F$500)} -> 4 | C6: {=SUMPRODUCT((site_model_risk!$C$2:$C$500=$A6)*(site_model_risk!$E$2:$E$500=C$2)*site_model_risk!$F$2:$F$500)} -> 5 | D6: {=SUMPRODUCT((site_model_risk!$C$2:$C$500=$A6)*(site_model_risk!$E$2:$E$500=D$2)*site_model_risk!$F$2:$F$500)} -> 0 | E6: {=SUMPRODUCT((site_model_risk!$C$2:$C$500=$A6)*(site_model_risk!$E$2:$E$500=E$2)*site_model_risk!$F$2:$F$500)} -> 2 | F6: =MAX(B6:E6)-MIN(B6:E6) -> 5 | G6: =IF(MAX(B6:E6)>=30,"Critical",IF(MAX(B6:E6)>=20,"High Risk",IF(MAX(B6:E6)>=10,"Medium Risk","Low Risk"))) -> Low Risk
A7: Bol.com | B7: {=SUMPRODUCT((site_model_risk!$C$2:$C$500=A7)*(site_model_risk!$E$2:$E$500=B$2)*site_model_risk!$F$2:$F$500)} -> 5 | C7: {=SUMPRODUCT((site_model_risk!$C$2:$C$500=$A7)*(site_model_risk!$E$2:$E$500=C$2)*site_model_risk!$F$2:$F$500)} -> 5 | D7: {=SUMPRODUCT((site_model_risk!$C$2:$C$500=$A7)*(site_model_risk!$E$2:$E$500=D$2)*site_model_risk!$F$2:$F$500)} -> 5 | E7: {=SUMPRODUCT((site_model_risk!$C$2:$C$500=$A7)*(site_model_risk!$E$2:$E$500=E$2)*site_model_risk!$F$2:$F$500)} -> 2 | F7: =MAX(B7:E7)-MIN(B7:E7) -> 3 | G7: =IF(MAX(B7:E7)>=30,"Critical",IF(MAX(B7:E7)>=20,"High Risk",IF(MAX(B7:E7)>=10,"Medium Risk","Low Risk"))) -> Low Risk
A8: Boozt | B8: {=SUMPRODUCT((site_model_risk!$C$2:$C$500=A8)*(site_model_risk!$E$2:$E$500=B$2)*site_model_risk!$F$2:$F$500)} -> 3 | C8: {=SUMPRODUCT((site_model_risk!$C$2:$C$500=$A8)*(site_model_risk!$E$2:$E$500=C$2)*site_model_risk!$F$2:$F$500)} -> 0 | D8: {=SUMPRODUCT((site_model_risk!$C$2:$C$500=$A8)*(site_model_risk!$E$2:$E$500=D$2)*site_model_risk!$F$2:$F$500)} -> 2 | E8: {=SUMPRODUCT((site_model_risk!$C$2:$C$500=$A8)*(site_model_risk!$E$2:$E$500=E$2)*site_model_risk!$F$2:$F$500)} -> 2 | F8: =MAX(B8:E8)-MIN(B8:E8) -> 3 | G8: =IF(MAX(B8:E8)>=30,"Critical",IF(MAX(B8:E8)>=20,"High Risk",IF(MAX(B8:E8)>=10,"Medium Risk","Low Risk"))) -> Low Risk
A9: Carrefour | B9: {=SUMPRODUCT((site_model_risk!$C$2:$C$500=A9)*(site_model_risk!$E$2:$E$500=B$2)*site_model_risk!$F$2:$F$500)} -> 5 | C9: {=SUMPRODUCT((site_model_risk!$C$2:$C$500=$A9)*(site_model_risk!$E$2:$E$500=C$2)*site_model_risk!$F$2:$F$500)} -> 3 | D9: {=SUMPRODUCT((site_model_risk!$C$2:$C$500=$A9)*(site_model_risk!$E$2:$E$500=D$2)*site_model_risk!$F$2:$F$500)} -> 5 | E9: {=SUMPRODUCT((site_model_risk!$C$2:$C$500=$A9)*(site_model_risk!$E$2:$E$500=E$2)*site_model_risk!$F$2:$F$500)} -> 2 | F9: =MAX(B9:E9)-MIN(B9:E9) -> 3 | G9: =IF(MAX(B9:E9)>=30,"Critical",IF(MAX(B9:E9)>=20,"High Risk",IF(MAX(B9:E9)>=10,"Medium Risk","Low Risk"))) -> Low Risk
A10: Cdiscount | B10: {=SUMPRODUCT((site_model_risk!$C$2:$C$500=A10)*(site_model_risk!$E$2:$E$500=B$2)*site_model_risk!$F$2:$F$500)} -> 5 | C10: {=SUMPRODUCT((site_model_risk!$C$2:$C$500=$A10)*(site_model_risk!$E$2:$E$500=C$2)*site_model_risk!$F$2:$F$500)} -> 7 | D10: {=SUMPRODUCT((site_model_risk!$C$2:$C$500=$A10)*(site_model_risk!$E$2:$E$500=D$2)*site_model_risk!$F$2:$F$500)} -> 5 | E10: {=SUMPRODUCT((site_model_risk!$C$2:$C$500=$A10)*(site_model_risk!$E$2:$E$500=E$2)*site_model_risk!$F$2:$F$500)} -> 2 | F10: =MAX(B10:E10)-MIN(B10:E10) -> 5 | G10: =IF(MAX(B10:E10)>=30,"Critical",IF(MAX(B10:E10)>=20,"High Risk",IF(MAX(B10:E10)>=10,"Medium Risk","Low Risk"))) -> Low Risk
A11: Decathlon | B11: {=SUMPRODUCT((site_model_risk!$C$2:$C$500=A11)*(site_model_risk!$E$2:$E$500=B$2)*site_model_risk!$F$2:$F$500)} -> 5 | C11: {=SUMPRODUCT((site_model_risk!$C$2:$C$500=$A11)*(site_model_risk!$E$2:$E$500=C$2)*site_model_risk!$F$2:$F$500)} -> 13 | D11: {=SUMPRODUCT((site_model_risk!$C$2:$C$500=$A11)*(site_model_risk!$E$2:$E$500=D$2)*site_model_risk!$F$2:$F$500)} -> 11 | E11: {=SUMPRODUCT((site_model_risk!$C$2:$C$500=$A11)*(site_model_risk!$E$2:$E$500=E$2)*site_model_risk!$F$2:$F$500)} -> 2 | F11: =MAX(B11:E11)-MIN(B11:E11) -> 11 | G11: =IF(MAX(B11:E11)>=30,"Critical",IF(MAX(B11:E11)>=20,"High Risk",IF(MAX(B11:E11)>=10,"Medium Risk","Low Risk"))) -> Medium Risk
A12: Douglas | B12: {=SUMPRODUCT((site_model_risk!$C$2:$C$500=A12)*(site_model_risk!$E$2:$E$500=B$2)*site_model_risk!$F$2:$F$500)} -> 8 | C12: {=SUMPRODUCT((site_model_risk!$C$2:$C$500=$A12)*(site_model_risk!$E$2:$E$500=C$2)*site_model_risk!$F$2:$F$500)} -> 5 | D12: {=SUMPRODUCT((site_model_risk!$C$2:$C$500=$A12)*(site_model_risk!$E$2:$E$500=D$2)*site_model_risk!$F$2:$F$500)} -> 13 | E12: {=SUMPRODUCT((site_model_risk!$C$2:$C$500=$A12)*(site_model_risk!$E$2:$E$500=E$2)*site_model_risk!$F$2:$F$500)} -> 2 | F12: =MAX(B12:E12)-MIN(B12:E12) -> 11 | G12: =IF(MAX(B12:E12)>=30,"Critical",IF(MAX(B12:E12)>=20,"High Risk",IF(MAX(B12:E12)>=10,"Medium Risk","Low Risk"))) -> Medium Risk
A13: El Corte Ingles | B13: {=SUMPRODUCT((site_model_risk!$C$2:$C$500=A13)*(site_model_risk!$E$2:$E$500=B$2)*site_model_risk!$F$2:$F$500)} -> 2 | C13: {=SUMPRODUCT((site_model_risk!$C$2:$C$500=$A13)*(site_model_risk!$E$2:$E$500=C$2)*site_model_risk!$F$2:$F$500)} -> 2 | D13: {=SUMPRODUCT((site_model_risk!$C$2:$C$500=$A13)*(site_model_risk!$E$2:$E$500=D$2)*site_model_risk!$F$2:$F$500)} -> 2 | E13: {=SUMPRODUCT((site_model_risk!$C$2:$C$500=$A13)*(site_model_risk!$E$2:$E$500=E$2)*site_model_risk!$F$2:$F$500)} -> 2 | F13: =MAX(B13:E13)-MIN(B13:E13) -> 0 | G13: =IF(MAX(B13:E13)>=30,"Critical",IF(MAX(B13:E13)>=20,"High Risk",IF(MAX(B13:E13)>=10,"Medium Risk","Low Risk"))) -> Low Risk
A14: eMAG | B14: {=SUMPRODUCT((site_model_risk!$C$2:$C$500=A14)*(site_model_risk!$E$2:$E$500=B$2)*site_model_risk!$F$2:$F$500)} -> 3 | C14: {=SUMPRODUCT((site_model_risk!$C$2:$C$500=$A14)*(site_model_risk!$E$2:$E$500=C$2)*site_model_risk!$F$2:$F$500)} -> 2 | D14: {=SUMPRODUCT((site_model_risk!$C$2:$C$500=$A14)*(site_model_risk!$E$2:$E$500=D$2)*site_model_risk!$F$2:$F$500)} -> 15 | E14: {=SUMPRODUCT((site_model_risk!$C$2:$C$500=$A14)*(site_model_risk!$E$2:$E$500=E$2)*site_model_risk!$F$2:$F$500)} -> 2 | F14: =MAX(B14:E14)-MIN(B14:E14) -> 13 | G14: =IF(MAX(B14:E14)>=30,"Critical",IF(MAX(B14:E14)>=20,"High Risk",IF(MAX(B14:E14)>=10,"Medium Risk","Low Risk"))) -> Medium Risk
... A22: Zooplus | B22: {=SUMPRODUCT((site_model_risk!$C$2:$C$500=A22)*(site_model_risk!$E$2:$E$500=B$2)*site_model_risk!$F$2:$F$500)} -> 3 | C22: {=SUMPRODUCT((site_model_risk!$C$2:$C$500=$A22)*(site_model_risk!$E$2:$E$500=C$2)*site_model_risk!$F$2:$F$500)} -> 5 | D22: {=SUMPRODUCT((site_model_risk!$C$2:$C$500=$A22)*(site_model_risk!$E$2:$E$500=D$2)*site_model_risk!$F$2:$F$500)} -> 9 | E22: {=SUMPRODUCT((site_model_risk!$C$2:$C$500=$A22)*(site_model_risk!$E$2:$E$500=E$2)*site_model_risk!$F$2:$F$500)} -> 2 | F22: =MAX(B22:E22)-MIN(B22:E22) -> 7 | G22: =IF(MAX(B22:E22)>=30,"Critical",IF(MAX(B22:E22)>=20,"High Risk",IF(MAX(B22:E22)>=10,"Medium Risk","Low Risk"))) -> Low Risk

Sheet Table 23
A1: Table 23. Pairwise Agreement Between Models
A2: model_a | B2: model_b | D2: pairwise_agreement | E2: n_cases
A3: CLAUDE | B3: LLAMA | C3: Claude 4.6 – Llama 3.3 | D3: 0.96470588 | E3: 340
A4: GEMINI | B4: LLAMA | C4: Gemini 2.5 – Llama 3.3 | D4: 0.94117647 | E4: 340
A5: CLAUDE | B5: GEMINI | C5: Claude 4.6 – Gemini 2.5 | D5: 0.92222222 | E5: 360
A6: GPT | B6: LLAMA | C6: GPT-4o – Llama 3.3 | D6: 0.92058824 | E6: 340
A7: CLAUDE | B7: GPT | C7: Claude 4.6 – GPT-4o | D7: 0.90555556 | E7: 360
A8: GEMINI | B8: GPT | C8: Gemini 2.5 – GPT-4o | D8: 0.88888889 | E8: 360

Sheet Table 24
A1: Table 24. Indicator-Level Divergence
A2: ID | B2: Indicator | C2: Divergence
A3: R03 | B3: Demonstrability of consent | C3: 0.55
A4: R04 | B4: Specific consent (granularity) | C4: 0.35
A5: R13 | B5: Data retention period | C5: 0.35
A6: R12 | B6: International transfers | C6: 0.3
A7: R17 | B7: Equal prominence of choices | C7: 0.25
A8: R10 | B8: Legal basis disclosure | C8: 0.2
A9: R11 | B9: Third-party recipients | C9: 0.15
A10: R16 | B10: Pre-consent tracking | C10: 0.15
A11: R02 | B11: Right to withdraw | C11: 0.1
A12: R01 | B12: Freely given consent | C12: 0.05
A13: R09 | B13: Purpose specification | C13: 0.05
A14: R15 | B14: Complaint mechanism | C14: 0.05
... A20: R14 | B20: Data subject rights | C20: 0

Sheet Table 25
A1: Table 25. Fleiss' Kappa by Indicator
A2: indicator_id | B2: indicator | C2: fleiss_kappa
A3: R01 | B3: Freely Given Consent | C3: 0.75975976
A4: R02 | B4: Right to Withdraw | C4: -0.025641026
A5: R03 | B5: Demonstrability of Consent | C5: 0.13978495
A6: R04 | B6: Specific Consent | C6: 0.040166927
A7: R09 | B7: Purpose Specification | C7: -0.012658228
A8: R10 | B8: Legal Basis Disclosure | C8: -0.052631579
A9: R11 | B9: Third-Party Recipients | C9: -0.038961039
A10: R12 | B10: International Transfers | C10: -0.081081081
A11: R13 | B11: Data Retention Period | C11: 0.085714286
A12: R15 | B12: Complaint Mechanism | C12: -0.012658228
A13: R16 | B13: Pre-Consent Tracking | C13: -0.038961039
A14: R17 | B14: Equal prominence of choices | C14: 0.615
A15: R18 | B15: Layered Information | C15: 0.31623932

Sheet Table 26
A1: Table 26. Sites with Meaningful Divergence (Weighted Range)
A2: Site | B2: Claude | C2: Gemini | D2: GPT | E2: Llama | F2: Weighted Range
A3: eMAG | B3: {=SUMPRODUCT((site_model_risk!$C$2:$C$500=$A3)*(site_model_risk!$E$2:$E$500=B$2)*site_model_risk!$F$2:$F$500)} -> 3 | C3: {=SUMPRODUCT((site_model_risk!$C$2:$C$500=$A3)*(site_model_risk!$E$2:$E$500=C$2)*site_model_risk!$F$2:$F$500)} -> 2 | D3: {=SUMPRODUCT((site_model_risk!$C$2:$C$500=$A3)*(site_model_risk!$E$2:$E$500=D$2)*site_model_risk!$F$2:$F$500)} -> 15 | E3: {=SUMPRODUCT((site_model_risk!$C$2:$C$500=$A3)*(site_model_risk!$E$2:$E$500=E$2)*site_model_risk!$F$2:$F$500)} -> 2 | F3: =MAX(B3:E3)-MIN(B3:E3) -> 13
A4: Douglas | B4: {=SUMPRODUCT((site_model_risk!$C$2:$C$500=$A4)*(site_model_risk!$E$2:$E$500=B$2)*site_model_risk!$F$2:$F$500)} -> 8 | C4: {=SUMPRODUCT((site_model_risk!$C$2:$C$500=$A4)*(site_model_risk!$E$2:$E$500=C$2)*site_model_risk!$F$2:$F$500)} -> 5 | D4: {=SUMPRODUCT((site_model_risk!$C$2:$C$500=$A4)*(site_model_risk!$E$2:$E$500=D$2)*site_model_risk!$F$2:$F$500)} -> 13 | E4: {=SUMPRODUCT((site_model_risk!$C$2:$C$500=$A4)*(site_model_risk!$E$2:$E$500=E$2)*site_model_risk!$F$2:$F$500)} -> 2 | F4: =MAX(B4:E4)-MIN(B4:E4) -> 11
A5: Decathlon | B5: {=SUMPRODUCT((site_model_risk!$C$2:$C$500=$A5)*(site_model_risk!$E$2:$E$500=B$2)*site_model_risk!$F$2:$F$500)} -> 5 | C5: {=SUMPRODUCT((site_model_risk!$C$2:$C$500=$A5)*(site_model_risk!$E$2:$E$500=C$2)*site_model_risk!$F$2:$F$500)} -> 13 | D5: {=SUMPRODUCT((site_model_risk!$C$2:$C$500=$A5)*(site_model_risk!$E$2:$E$500=D$2)*site_model_risk!$F$2:$F$500)} -> 11 | E5: {=SUMPRODUCT((site_model_risk!$C$2:$C$500=$A5)*(site_model_risk!$E$2:$E$500=E$2)*site_model_risk!$F$2:$F$500)} -> 2 | F5: =MAX(B5:E5)-MIN(B5:E5) -> 11
A6: Notino | B6: {=SUMPRODUCT((site_model_risk!$C$2:$C$500=$A6)*(site_model_risk!$E$2:$E$500=B$2)*site_model_risk!$F$2:$F$500)} -> 5 | C6: {=SUMPRODUCT((site_model_risk!$C$2:$C$500=$A6)*(site_model_risk!$E$2:$E$500=C$2)*site_model_risk!$F$2:$F$500)} -> 13 | D6: {=SUMPRODUCT((site_model_risk!$C$2:$C$500=$A6)*(site_model_risk!$E$2:$E$500=D$2)*site_model_risk!$F$2:$F$500)} -> 5 | E6: {=SUMPRODUCT((site_model_risk!$C$2:$C$500=$A6)*(site_model_risk!$E$2:$E$500=E$2)*site_model_risk!$F$2:$F$500)} -> 2 | F6: =MAX(B6:E6)-MIN(B6:E6) -> 11
A7: Smyths Toys | B7: {=SUMPRODUCT((site_model_risk!$C$2:$C$500=$A7)*(site_model_risk!$E$2:$E$500=B$2)*site_model_risk!$F$2:$F$500)} -> 6 | C7: {=SUMPRODUCT((site_model_risk!$C$2:$C$500=$A7)*(site_model_risk!$E$2:$E$500=C$2)*site_model_risk!$F$2:$F$500)} -> 2 | D7: {=SUMPRODUCT((site_model_risk!$C$2:$C$500=$A7)*(site_model_risk!$E$2:$E$500=D$2)*site_model_risk!$F$2:$F$500)} -> 10 | E7: {=SUMPRODUCT((site_model_risk!$C$2:$C$500=$A7)*(site_model_risk!$E$2:$E$500=E$2)*site_model_risk!$F$2:$F$500)} -> 2 | F7: =MAX(B7:E7)-MIN(B7:E7) -> 8
A8: Zooplus | B8: {=SUMPRODUCT((site_model_risk!$C$2:$C$500=$A8)*(site_model_risk!$E$2:$E$500=B$2)*site_model_risk!$F$2:$F$500)} -> 3 | C8: {=SUMPRODUCT((site_model_risk!$C$2:$C$500=$A8)*(site_model_risk!$E$2:$E$500=C$2)*site_model_risk!$F$2:$F$500)} -> 5 | D8: {=SUMPRODUCT((site_model_risk!$C$2:$C$500=$A8)*(site_model_risk!$E$2:$E$500=D$2)*site_model_risk!$F$2:$F$500)} -> 9 | E8: {=SUMPRODUCT((site_model_risk!$C$2:$C$500=$A8)*(site_model_risk!$E$2:$E$500=E$2)*site_model_risk!$F$2:$F$500)} -> 2 | F8: =MAX(B8:E8)-MIN(B8:E8) -> 7
A9: Otto | B9: {=SUMPRODUCT((site_model_risk!$C$2:$C$500=$A9)*(site_model_risk!$E$2:$E$500=B$2)*site_model_risk!$F$2:$F$500)} -> 3 | C9: {=SUMPRODUCT((site_model_risk!$C$2:$C$500=$A9)*(site_model_risk!$E$2:$E$500=C$2)*site_model_risk!$F$2:$F$500)} -> 8 | D9: {=SUMPRODUCT((site_model_risk!$C$2:$C$500=$A9)*(site_model_risk!$E$2:$E$500=D$2)*site_model_risk!$F$2:$F$500)} -> 8 | E9: {=SUMPRODUCT((site_model_risk!$C$2:$C$500=$A9)*(site_model_risk!$E$2:$E$500=E$2)*site_model_risk!$F$2:$F$500)} -> 2 | F9: =MAX(B9:E9)-MIN(B9:E9) -> 6
A10: Amazon | B10: {=SUMPRODUCT((site_model_risk!$C$2:$C$500=$A10)*(site_model_risk!$E$2:$E$500=B$2)*site_model_risk!$F$2:$F$500)} -> 5 | C10: {=SUMPRODUCT((site_model_risk!$C$2:$C$500=$A10)*(site_model_risk!$E$2:$E$500=C$2)*site_model_risk!$F$2:$F$500)} -> 8 | D10: {=SUMPRODUCT((site_model_risk!$C$2:$C$500=$A10)*(site_model_risk!$E$2:$E$500=D$2)*site_model_risk!$F$2:$F$500)} -> 5 | E10: {=SUMPRODUCT((site_model_risk!$C$2:$C$500=$A10)*(site_model_risk!$E$2:$E$500=E$2)*site_model_risk!$F$2:$F$500)} -> 0 | F10: =MAX(B10:E10)-MIN(B10:E10) -> 8
A11: Fnac | B11: {=SUMPRODUCT((site_model_risk!$C$2:$C$500=$A11)*(site_model_risk!$E$2:$E$500=B$2)*site_model_risk!$F$2:$F$500)} -> 8 | C11: {=SUMPRODUCT((site_model_risk!$C$2:$C$500=$A11)*(site_model_risk!$E$2:$E$500=C$2)*site_model_risk!$F$2:$F$500)} -> 5 | D11: {=SUMPRODUCT((site_model_risk!$C$2:$C$500=$A11)*(site_model_risk!$E$2:$E$500=D$2)*site_model_risk!$F$2:$F$500)} -> 5 | E11: {=SUMPRODUCT((site_model_risk!$C$2:$C$500=$A11)*(site_model_risk!$E$2:$E$500=E$2)*site_model_risk!$F$2:$F$500)} -> 2 | F11: =MAX(B11:E11)-MIN(B11:E11) -> 6
A15: Table 26. Sites with Meaningful Divergence (Unweighted)
A16: Site | B16: Claude | C16: Gemini | D16: GPT | E16: Llama | F16: Unweighted Range
A17: eMAG | B17: {=SUMPRODUCT((site_model_risk!$C$2:$C$500=$A17)*(site_model_risk!$E$2:$E$500=B$2)*site_model_risk!$G$2:$G$500)} -> 2 | C17: {=SUMPRODUCT((site_model_risk!$C$2:$C$500=$A17)*(site_model_risk!$E$2:$E$500=C$2)*site_model_risk!$G$2:$G$500)} -> 1 | D17: {=SUMPRODUCT((site_model_risk!$C$2:$C$500=$A17)*(site_model_risk!$E$2:$E$500=D$2)*site_model_risk!$G$2:$G$500)} -> 7 | E17: {=SUMPRODUCT((site_model_risk!$C$2:$C$500=$A17)*(site_model_risk!$E$2:$E$500=E$2)*site_model_risk!$G$2:$G$500)} -> 1 | F17: =MAX(B17:E17)-MIN(B17:E17) -> 6
A18: Douglas | B18: {=SUMPRODUCT((site_model_risk!$C$2:$C$500=$A18)*(site_model_risk!$E$2:$E$500=B$2)*site_model_risk!$G$2:$G$500)} -> 3 | C18: {=SUMPRODUCT((site_model_risk!$C$2:$C$500=$A18)*(site_model_risk!$E$2:$E$500=C$2)*site_model_risk!$G$2:$G$500)} -> 2 | D18: {=SUMPRODUCT((site_model_risk!$C$2:$C$500=$A18)*(site_model_risk!$E$2:$E$500=D$2)*site_model_risk!$G$2:$G$500)} -> 6 | E18: {=SUMPRODUCT((site_model_risk!$C$2:$C$500=$A18)*(site_model_risk!$E$2:$E$500=E$2)*site_model_risk!$G$2:$G$500)} -> 1 | F18: =MAX(B18:E18)-MIN(B18:E18) -> 5
A19: Decathlon | B19: {=SUMPRODUCT((site_model_risk!$C$2:$C$500=$A19)*(site_model_risk!$E$2:$E$500=B$2)*site_model_risk!$G$2:$G$500)} -> 2 | C19: {=SUMPRODUCT((site_model_risk!$C$2:$C$500=$A19)*(site_model_risk!$E$2:$E$500=C$2)*site_model_risk!$G$2:$G$500)} -> 5 | D19: {=SUMPRODUCT((site_model_risk!$C$2:$C$500=$A19)*(site_model_risk!$E$2:$E$500=D$2)*site_model_risk!$G$2:$G$500)} -> 4 | E19: {=SUMPRODUCT((site_model_risk!$C$2:$C$500=$A19)*(site_model_risk!$E$2:$E$500=E$2)*site_model_risk!$G$2:$G$500)} -> 1 | F19: =MAX(B19:E19)-MIN(B19:E19) -> 4
A20: Notino | B20: {=SUMPRODUCT((site_model_risk!$C$2:$C$500=$A20)*(site_model_risk!$E$2:$E$500=B$2)*site_model_risk!$G$2:$G$500)} -> 2 | C20: {=SUMPRODUCT((site_model_risk!$C$2:$C$500=$A20)*(site_model_risk!$E$2:$E$500=C$2)*site_model_risk!$G$2:$G$500)} -> 6 | D20: {=SUMPRODUCT((site_model_risk!$C$2:$C$500=$A20)*(site_model_risk!$E$2:$E$500=D$2)*site_model_risk!$G$2:$G$500)} -> 2 | E20: {=SUMPRODUCT((site_model_risk!$C$2:$C$500=$A20)*(site_model_risk!$E$2:$E$500=E$2)*site_model_risk!$G$2:$G$500)} -> 1 | F20: =MAX(B20:E20)-MIN(B20:E20) -> 5
A21: Smyths Toys | B21: {=SUMPRODUCT((site_model_risk!$C$2:$C$500=$A21)*(site_model_risk!$E$2:$E$500=B$2)*site_model_risk!$G$2:$G$500)} -> 3 | C21: {=SUMPRODUCT((site_model_risk!$C$2:$C$500=$A21)*(site_model_risk!$E$2:$E$500=C$2)*site_model_risk!$G$2:$G$500)} -> 1 | D21: {=SUMPRODUCT((site_model_risk!$C$2:$C$500=$A21)*(site_model_risk!$E$2:$E$500=D$2)*site_model_risk!$G$2:$G$500)} -> 5 | E21: {=SUMPRODUCT((site_model_risk!$C$2:$C$500=$A21)*(site_model_risk!$E$2:$E$500=E$2)*site_model_risk!$G$2:$G$500)} -> 1 | F21: =MAX(B21:E21)-MIN(B21:E21) -> 4
A22: Zooplus | B22: {=SUMPRODUCT((site_model_risk!$C$2:$C$500=$A22)*(site_model_risk!$E$2:$E$500=B$2)*site_model_risk!$G$2:$G$500)} -> 1 | C22: {=SUMPRODUCT((site_model_risk!$C$2:$C$500=$A22)*(site_model_risk!$E$2:$E$500=C$2)*site_model_risk!$G$2:$G$500)} -> 2 | D22: {=SUMPRODUCT((site_model_risk!$C$2:$C$500=$A22)*(site_model_risk!$E$2:$E$500=D$2)*site_model_risk!$G$2:$G$500)} -> 4 | E22: {=SUMPRODUCT((site_model_risk!$C$2:$C$500=$A22)*(site_model_risk!$E$2:$E$500=E$2)*site_model_risk!$G$2:$G$500)} -> 1 | F22: =MAX(B22:E22)-MIN(B22:E22) -> 3
A23: Otto | B23: {=SUMPRODUCT((site_model_risk!$C$2:$C$500=$A23)*(site_model_risk!$E$2:$E$500=B$2)*site_model_risk!$G$2:$G$500)} -> 1 | C23: {=SUMPRODUCT((site_model_risk!$C$2:$C$500=$A23)*(site_model_risk!$E$2:$E$500=C$2)*site_model_risk!$G$2:$G$500)} -> 3 | D23: {=SUMPRODUCT((site_model_risk!$C$2:$C$500=$A23)*(site_model_risk!$E$2:$E$500=D$2)*site_model_risk!$G$2:$G$500)} -> 3 | E23: {=SUMPRODUCT((site_model_risk!$C$2:$C$500=$A23)*(site_model_risk!$E$2:$E$500=E$2)*site_model_risk!$G$2:$G$500)} -> 1 | F23: =MAX(B23:E23)-MIN(B23:E23) -> 2
A24: Amazon | B24: {=SUMPRODUCT((site_model_risk!$C$2:$C$500=$A24)*(site_model_risk!$E$2:$E$500=B$2)*site_model_risk!$G$2:$G$500)} -> 2 | C24: {=SUMPRODUCT((site_model_risk!$C$2:$C$500=$A24)*(site_model_risk!$E$2:$E$500=C$2)*site_model_risk!$G$2:$G$500)} -> 3 | D24: {=SUMPRODUCT((site_model_risk!$C$2:$C$500=$A24)*(site_model_risk!$E$2:$E$500=D$2)*site_model_risk!$G$2:$G$500)} -> 2 | E24: {=SUMPRODUCT((site_model_risk!$C$2:$C$500=$A24)*(site_model_risk!$E$2:$E$500=E$2)*site_model_risk!$G$2:$G$500)} -> 0 | F24: =MAX(B24:E24)-MIN(B24:E24) -> 3
A25: Fnac | B25: {=SUMPRODUCT((site_model_risk!$C$2:$C$500=$A25)*(site_model_risk!$E$2:$E$500=B$2)*site_model_risk!$G$2:$G$500)} -> 3 | C25: {=SUMPRODUCT((site_model_risk!$C$2:$C$500=$A25)*(site_model_risk!$E$2:$E$500=C$2)*site_model_risk!$G$2:$G$500)} -> 2 | D25: {=SUMPRODUCT((site_model_risk!$C$2:$C$500=$A25)*(site_model_risk!$E$2:$E$500=D$2)*site_model_risk!$G$2:$G$500)} -> 2 | E25: {=SUMPRODUCT((site_model_risk!$C$2:$C$500=$A25)*(site_model_risk!$E$2:$E$500=E$2)*site_model_risk!$G$2:$G$500)} -> 1 | F25: =MAX(B25:E25)-MIN(B25:E25) -> 2

Sheet risk_score_divergence
A1: run_type | B1: run_no | C1: site_name | D1: domain | E1: min_unweighted_risk_score | F1: max_unweighted_risk_score | G1: min_weighted_risk_score | H1: max_weighted_risk_score | I1: n_models | J1: unweighted_risk_score_range | K1: weighted_risk_score_range | L1: meaningful_unweighted_divergence
A2: main | B2: 1 | C2: About You | D2: aboutyou.de | E2: 1 | F2: 3 | G2: 3 | H2: 8 | I2: 4 | J2: 2 | K2: 5 | L2: FALSE
A3: main | B3: 1 | C3: Allegro | D3: allegro.pl | E3: 1 | F3: 2 | G3: 2 | H3: 5 | I3: 4 | J3: 1 | K3: 3 | L3: FALSE
A4: main | B4: 1 | C4: Amazon | D4: amazon.de | E4: 0 | F4: 3 | G4: 0 | H4: 8 | I4: 4 | J4: 3 | K4: 8 | L4: FALSE
A5: main | B5: 1 | C5: Answear | D5: answear.com | E5: 0 | F5: 2 | G5: 0 | H5: 5 | I5: 4 | J5: 2 | K5: 5 | L5: FALSE
A6: main | B6: 1 | C6: Bol.com | D6: bol.com | E6: 1 | F6: 2 | G6: 2 | H6: 5 | I6: 4 | J6: 1 | K6: 3 | L6: FALSE
A7: main | B7: 1 | C7: Boozt | D7: boozt.com | E7: 0 | F7: 1 | G7: 0 | H7: 3 | I7: 4 | J7: 1 | K7: 3 | L7: FALSE
A8: main | B8: 1 | C8: Carrefour | D8: carrefour.fr | E8: 1 | F8: 2 | G8: 2 | H8: 5 | I8: 4 | J8: 1 | K8: 3 | L8: FALSE
A9: main | B9: 1 | C9: Cdiscount | D9: cdiscount.com | E9: 1 | F9: 3 | G9: 2 | H9: 7 | I9: 4 | J9: 2 | K9: 5 | L9: FALSE
A10: main | B10: 1 | C10: Decathlon | D10: decathlon.es | E10: 1 | F10: 5 | G10: 2 | H10: 13 | I10: 4 | J10: 4 | K10: 11 | L10: TRUE
A11: main | B11: 1 | C11: Douglas | D11: douglas.de | E11: 1 | F11: 6 | G11: 2 | H11: 13 | I11: 4 | J11: 5 | K11: 11 | L11: TRUE
A12: main | B12: 1 | C12: El Corte Ingles | D12: elcorteingles.es | E12: 1 | F12: 1 | G12: 2 | H12: 2 | I12: 4 | J12: 0 | K12: 0 | L12: FALSE
A13: main | B13: 1 | C13: eMAG | D13: emag.ro | E13: 1 | F13: 7 | G13: 2 | H13: 15 | I13: 4 | J13: 6 | K13: 13 | L13: TRUE
... A21: main | B21: 1 | C21: Zooplus | D21: zooplus.de | E21: 1 | F21: 4 | G21: 2 | H21: 9 | I21: 4 | J21: 3 | K21: 7 | L21: FALSE

Sheet pairwise_agreement
A1: run_type | B1: run_no | C1: model_a | D1: model_b | E1: pairwise_agreement | F1: n_cases
A2: main | B2: 1 | C2: CLAUDE | D2: GEMINI | E2: 0.92222222 | F2: 360
A3: main | B3: 1 | C3: CLAUDE | D3: GPT | E3: 0.90555556 | F3: 360
A4: main | B4: 1 | C4: CLAUDE | D4: LLAMA | E4: 0.96470588 | F4: 340
A5: main | B5: 1 | C5: GEMINI | D5: GPT | E5: 0.88888889 | F5: 360
A6: main | B6: 1 | C6: GEMINI | D6: LLAMA | E6: 0.94117647 | F6: 340
A7: main | B7: 1 | C7: GPT | D7: LLAMA | E7: 0.92058824 | F7: 340

Sheet indicator_model
A1: run_type | B1: run_no | C1: indicator_id | D1: indicator_name | E1: model | F1: mean_score | G1: total_flags | H1: hallucination_count | I1: validation_denominator | J1: hallucination_rate
A2: main | B2: 1 | C2: R01 | D2: Freely given consent | E2: CLAUDE | F2: 0.05 | G2: 1 | H2: 0 | I2: 8 | J2: 0
A3: main | B3: 1 | C3: R01 | D3: Freely given consent | E3: GEMINI | F3: 0.1 | G3: 2 | H3: 0 | I3: 13 | J3: 0
A4: main | B4: 1 | C4: R01 | D4: Freely given consent | E4: GPT | F4: 0.1 | G4: 2 | H4: 0 | I4: 2 | J4: 0 | M4: =SUMIFS($G$2:$G$72, $E$2:$E$72, "GPT", $C$2:$C$72, ">=R01", $C$2:$C$72, "<=R06") -> 27
A5: main | B5: 1 | C5: R01 | D5: Freely given consent | E5: LLAMA | F5: 0.05 | G5: 1 | H5: 0 | I5: 2 | J5: 0
A6: main | B6: 1 | C6: R02 | D6: Right to withdraw | E6: CLAUDE | F6: 0 | G6: 0 | H6: 0 | I6: 20 | J6: 0
A7: main | B7: 1 | C7: R02 | D7: Right to withdraw | E7: GEMINI | F7: 0.1 | G7: 2 | H7: 0 | I7: 20 | J7: 0
A8: main | B8: 1 | C8: R02 | D8: Right to withdraw | E8: GPT | F8: 0 | G8: 0 | H8: 0 | I8: 16 | J8: 0
A9: main | B9: 1 | C9: R02 | D9: Right to withdraw | E9: LLAMA | F9: 0 | G9: 0 | H9: 0 | I9: 20 | J9: 0
A10: main | B10: 1 | C10: R03 | D10: Demonstrability of consent | E10: CLAUDE | F10: 0.7 | G10: 14 | H10: 0 | I10: 20 | J10: 0
A11: main | B11: 1 | C11: R03 | D11: Demonstrability of consent | E11: GEMINI | F11: 0.6 | G11: 12 | H11: 0 | I11: 20 | J11: 0
A12: main | B12: 1 | C12: R03 | D12: Demonstrability of consent | E12: GPT | F12: 0.9 | G12: 18 | H12: 0 | I12: 20 | J12: 0
A13: main | B13: 1 | C13: R03 | D13: Demonstrability of consent | E13: LLAMA | F13: 0.9 | G13: 18 | H13: 0 | I13: 20 | J13: 0
A14: main | B14: 1 | C14: R04 | D14: Specific consent (granularity) | E14: CLAUDE | F14: 0 | G14: 0 | H14: 0 | I14: 20 | J14: 0
A15: main | B15: 1 | C15: R04 | D15: Specific consent (granularity) | E15: GEMINI | F15: 0.1 | G15: 2 | H15: 0 | I15: 19 | J15: 0
A16: main | B16: 1 | C16: R04 | D16: Specific consent (granularity) | E16: GPT | F16: 0.35 | G16: 7 | H16: 1 | I16: 16 | J16: 0.0625
... A72: main | B72: 1 | C72: R18 | D72: Layered information / clarity of information | E72: LLAMA | F72: 0 | G72: 0 | H72: 1 | I72: 20 | J72: 0.05

Sheet processing_stats
A1: run_type | B1: run_no | C1: model | D1: avg_chunk_count | E1: avg_chunk_coverage | F1: total_hallucinations | G1: validation_denominator | H1: indicator_rows | I1: hallucination_rate
A2: main | B2: 1 | C2: CLAUDE | D2: 2.25 | E2: 1 | F2: 0 | G2: 324 | H2: 360 | I2: 0
A3: main | B3: 1 | C3: GEMINI | D3: 2.25 | E3: 0.89583333 | F3: 2 | G3: 341 | H3: 360 | I3: 0.0058651026
A4: main | B4: 1 | C4: GPT | D4: 2.25 | E4: 1 | F4: 10 | G4: 322 | H4: 360 | I4: 0.031055901
A5: main | B5: 1 | C5: LLAMA | D5: 2.25 | E5: 1 | F5: 1 | G5: 294 | H5: 340 | I5: 0.0034013605

Sheet disagreement
A1: run_type | B1: run_no | C1: indicator_id | D1: disagreement_cases | E1: total_cases | F1: disagreement_rate
A2: main | B2: 1 | C2: R01 | D2: 1 | E2: 20 | F2: 0.05
A3: main | B3: 1 | C3: R02 | D3: 2 | E3: 20 | F3: 0.1
A4: main | B4: 1 | C4: R03 | D4: 11 | E4: 20 | F4: 0.55
A5: main | B5: 1 | C5: R04 | D5: 7 | E5: 20 | F5: 0.35
A6: main | B6: 1 | C6: R05 | D6: 0 | E6: 20 | F6: 0
A7: main | B7: 1 | C7: R06 | D7: 0 | E7: 20 | F7: 0
A8: main | B8: 1 | C8: R07 | D8: 0 | E8: 20 | F8: 0
A9: main | B9: 1 | C9: R08 | D9: 0 | E9: 20 | F9: 0
A10: main | B10: 1 | C10: R09 | D10: 1 | E10: 20 | F10: 0.05
A11: main | B11: 1 | C11: R10 | D11: 4 | E11: 20 | F11: 0.2
A12: main | B12: 1 | C12: R11 | D12: 3 | E12: 20 | F12: 0.15
A13: main | B13: 1 | C13: R12 | D13: 6 | E13: 20 | F13: 0.3
... A19: main | B19: 1 | C19: R18 | D19: 1 | E19: 20 | F19: 0.05

Sheet fleiss_kappa
A1: run_type | B1: run_no | C1: indicator_id | D1: fleiss_kappa | E1: n_sites | F1: n_models
A2: main | B2: 1 | C2: R01 | D2: 0.75975976 | E2: 20 | F2: 4
A3: main | B3: 1 | C3: R02 | D3: -0.025641026 | E3: 20 | F3: 4
A4: main | B4: 1 | C4: R03 | D4: 0.13978495 | E4: 20 | F4: 4
A5: main | B5: 1 | C5: R04 | D5: 0.040166927 | E5: 20 | F5: 4
A6: main | B6: 1 | C6: R05 | E6: 20 | F6: 4
A7: main | B7: 1 | C7: R06 | E7: 20 | F7: 4
A8: main | B8: 1 | C8: R07 | E8: 20 | F8: 4
A9: main | B9: 1 | C9: R08 | E9: 20 | F9: 4
A10: main | B10: 1 | C10: R09 | D10: -0.012658228 | E10: 20 | F10: 4
A11: main | B11: 1 | C11: R10 | D11: -0.052631579 | E11: 20 | F11: 4
A12: main | B12: 1 | C12: R11 | D12: -0.038961039 | E12: 20 | F12: 4
A13: main | B13: 1 | C13: R12 | D13: -0.081081081 | E13: 20 | F13: 4
A14: main | B14: 1 | C14: R13 | D14: 0.085714286 | E14: 20 | F14: 4
A15: main | B15: 1 | C15: R14 | E15: 20 | F15: 4
A16: main | B16: 1 | C16: R15 | D16: -0.012658228 | E16: 20 | F16: 4
A17: main | B17: 1 | C17: R16 | D17: -0.038961039 | E17: 20 | F17: 4
A18: main | B18: 1 | C18: R17 | E18: 0 | F18: 4
A19: main | B19: 1 | C19: R18 | D19: 0.31623932 | E19: 20 | F19: 4

Sheet hallucination_by_model
A1: run_type | B1: run_no | C1: model | D1: AE | E1: H | F1: MC | G1: VC | H1: validation_denominator | I1: hallucination_rate | J1: groundedness_rate
A2: main | B2: 1 | C2: CLAUDE | D2: 36 | E2: 0 | F2: 6 | G2: 318 | H2: 324 | I2: 0 | J2: 1
A3: main | B3: 1 | C3: GEMINI | D3: 19 | E3: 2 | F3: 22 | G3: 317 | H3: 341 | I3: 0.0058651026 | J3: 0.9941349
A4: main | B4: 1 | C4: GPT | D4: 38 | E4: 10 | F4: 28 | G4: 284 | H4: 322 | I4: 0.031055901 | J4: 0.9689441
A5: main | B5: 1 | C5: LLAMA | D5: 46 | E5: 1 | F5: 10 | G5: 283 | H5: 294 | I5: 0.0034013605 | J5: 0.99659864

Sheet Table 27
A1: Table 27. Output Stability Across Three Runs (10 sites, all applicable indicators)
A2: model | B2: model | C2: stable_cases | D2: total_cases | E2: stability_rate
A3: CLAUDE | B3: Claude 4.6 | C3: 180 | D3: 180 | E3: 1
A4: LLAMA | B4: Llama 3.3 70B | C4: 166 | D4: 170 | E4: 0.97647059
A5: GPT | B5: GPT-4o | C5: 173 | D5: 180 | E5: 0.96111111
A6: GEMINI | B6: Gemini 2.5 Flash | C6: 171 | D6: 180 | E6: 0.95

Sheet Table 28
A1: Table 28. Unstable Indicators by Model (Stability Rate < 100%)
A2: model | B2: indicator_id | C2: stable_cases | D2: total_cases | E2: stability_rate
A3: LLAMA | B3: R03 | C3: 7 | D3: 10 | E3: 0.7
A4: LLAMA | B4: R12 | C4: 9 | D4: 10 | E4: 0.9
A5: GPT | B5: R12 | C5: 8 | D5: 10 | E5: 0.8
A6: GPT | B6: R17 | C6: 8 | D6: 10 | E6: 0.8
A7: GPT | B7: R01 | C7: 9 | D7: 10 | E7: 0.9
A8: GPT | B8: R05 | C8: 9 | D8: 10 | E8: 0.9
A9: GPT | B9: R11 | C9: 9 | D9: 10 | E9: 0.9
A10: GEMINI | B10: R04 | C10: 8 | D10: 10 | E10: 0.8
A11: GEMINI | B11: R16 | C11: 8 | D11: 10 | E11: 0.8
A12: GEMINI | B12: R01 | C12: 9 | D12: 10 | E12: 0.9
A13: GEMINI | B13: R03 | C13: 9 | D13: 10 | E13: 0.9
A14: GEMINI | B14: R10 | C14: 9 | D14: 10 | E14: 0.9
... A16: GEMINI | B16: R13 | C16: 9 | D16: 10 | E16: 0.9

Sheet Table 29
A1: Table 29. Hallucination Rate by Model (full dataset)
A2: model | B2: Model | C2: VC | D2: MC | E2: H | F2: AE | G2: validation_denominator | H2: hallucination_rate | I2: groundedness_rate
A3: CLAUDE | B3: Claude 4.6 | C3: 318 | D3: 6 | E3: 0 | F3: 36 | G3: 324 | H3: 0 | I3: 1
A4: LLAMA | B4: Llama 3.3 70B | C4: 283 | D4: 10 | E4: 1 | F4: 46 | G4: 294 | H4: 0.0034013605 | I4: 0.99659864
A5: GEMINI | B5: Gemini 2.5 Flash | C5: 317 | D5: 22 | E5: 2 | F5: 19 | G5: 341 | H5: 0.0058651026 | I5: 0.9941349
A6: GPT | B6: GPT-4o | C6: 284 | D6: 28 | E6: 10 | F6: 38 | G6: 322 | H6: 0.031055901 | I6: 0.9689441

Sheet hallucination_by_indicator
A1: run_type | B1: run_no | C1: model | D1: indicator_id | E1: indicator_name | F1: AE | G1: H | H1: MC | I1: VC | J1: validation_denominator | K1: hallucination_rate | L1: groundedness_rate
A2: main | B2: 1 | C2: CLAUDE | D2: R01 | E2: Freely given consent | F2: 12 | G2: 0 | H2: 1 | I2: 7 | J2: 8 | K2: 0 | L2: 1
A3: main | B3: 1 | C3: CLAUDE | D3: R02 | E3: Right to withdraw | F3: 0 | G3: 0 | H3: 0 | I3: 20 | J3: 20 | K3: 0 | L3: 1
A4: main | B4: 1 | C4: CLAUDE | D4: R03 | E4: Demonstrability of consent | F4: 0 | G4: 0 | H4: 0 | I4: 20 | J4: 20 | K4: 0 | L4: 1
A5: main | B5: 1 | C5: CLAUDE | D5: R04 | E5: Specific consent (granularity) | F5: 0 | G5: 0 | H5: 0 | I5: 20 | J5: 20 | K5: 0 | L5: 1
A6: main | B6: 1 | C6: CLAUDE | D6: R05 | E6: Informed consent | F6: 0 | G6: 0 | H6: 0 | I6: 20 | J6: 20 | K6: 0 | L6: 1
A7: main | B7: 1 | C7: CLAUDE | D7: R06 | E7: Unambiguous indication | F7: 11 | G7: 0 | H7: 0 | I7: 9 | J7: 9 | K7: 0 | L7: 1
A8: main | B8: 1 | C8: CLAUDE | D8: R07 | E8: Identity of controller | F8: 0 | G8: 0 | H8: 0 | I8: 20 | J8: 20 | K8: 0 | L8: 1
A9: main | B9: 1 | C9: CLAUDE | D9: R08 | E9: Contact details | F9: 0 | G9: 0 | H9: 0 | I9: 20 | J9: 20 | K9: 0 | L9: 1
A10: main | B10: 1 | C10: CLAUDE | D10: R09 | E10: Purpose specification | F10: 0 | G10: 0 | H10: 0 | I10: 20 | J10: 20 | K10: 0 | L10: 1
A11: main | B11: 1 | C11: CLAUDE | D11: R10 | E11: Legal basis disclosure | F11: 0 | G11: 0 | H11: 0 | I11: 20 | J11: 20 | K11: 0 | L11: 1
A12: main | B12: 1 | C12: CLAUDE | D12: R11 | E12: Third-party recipients | F12: 0 | G12: 0 | H12: 0 | I12: 20 | J12: 20 | K12: 0 | L12: 1
A13: main | B13: 1 | C13: CLAUDE | D13: R12 | E13: International transfers | F13: 0 | G13: 0 | H13: 0 | I13: 20 | J13: 20 | K13: 0 | L13: 1
... A72: main | B72: 1 | C72: LLAMA | D72: R18 | E72: Layered information / clarity of information | F72: 0 | G72: 1 | H72: 0 | I72: 19 | J72: 20 | K72: 0.05 | L72: 0.95

Sheet human_alignment_by_model
A1: run_type | B1: run_no | C1: model | D1: human_validated_rows | E1: human_agreements | F1: human_disagreements | G1: human_alignment_rate
A2: main | B2: 1 | C2: CLAUDE | D2: 360 | E2: 354 | F2: 6 | G2: 0.98333333
A3: main | B3: 1 | C3: GEMINI | D3: 360 | E3: 338 | F3: 22 | G3: 0.93888889
A4: main | B4: 1 | C4: GPT | D4: 360 | E4: 330 | F4: 30 | G4: 0.91666667
A5: main | B5: 1 | C5: LLAMA | D5: 340 | E5: 330 | F5: 10 | G5: 0.97058824

Sheet Table 30
A1: Table 30. LLM Trustworthiness Profile
A2: model | B2: groundedness_rate | C2: stability_rate | D2: human_alignment_rate
A3: CLAUDE | B3: =_xlfn.XLOOKUP($A3,hallucination_by_model!$C$2:$C$5,hallucination_by_model!$J$2:$J$5,1,0) -> 1 | C3: =_xlfn.XLOOKUP($A3,stability_by_model!$A$2:$A$5,stability_by_model!$D$2:$D$5,1,0) -> 1 | D3: =_xlfn.XLOOKUP($A3,human_alignment_by_model!$C$2:$C$5,human_alignment_by_model!$G$2:$G$5,1,0) -> 0.98333333
A4: GEMINI | B4: =_xlfn.XLOOKUP($A4,hallucination_by_model!$C$2:$C$5,hallucination_by_model!$J$2:$J$5,1,0) -> 0.9941349 | C4: =_xlfn.XLOOKUP($A4,stability_by_model!$A$2:$A$5,stability_by_model!$D$2:$D$5,1,0) -> 0.95 | D4: =_xlfn.XLOOKUP($A4,human_alignment_by_model!$C$2:$C$5,human_alignment_by_model!$G$2:$G$5,1,0) -> 0.93888889
A5: LLAMA | B5: =_xlfn.XLOOKUP($A5,hallucination_by_model!$C$2:$C$5,hallucination_by_model!$J$2:$J$5,1,0) -> 0.99659864 | C5: =_xlfn.XLOOKUP($A5,stability_by_model!$A$2:$A$5,stability_by_model!$D$2:$D$5,1,0) -> 0.97647059 | D5: =_xlfn.XLOOKUP($A5,human_alignment_by_model!$C$2:$C$5,human_alignment_by_model!$G$2:$G$5,1,0) -> 0.97058824
A6: GPT | B6: =_xlfn.XLOOKUP($A6,hallucination_by_model!$C$2:$C$5,hallucination_by_model!$J$2:$J$5,1,0) -> 0.9689441 | C6: =_xlfn.XLOOKUP($A6,stability_by_model!$A$2:$A$5,stability_by_model!$D$2:$D$5,1,0) -> 0.96111111 | D6: =_xlfn.XLOOKUP($A6,human_alignment_by_model!$C$2:$C$5,human_alignment_by_model!$G$2:$G$5,1,0) -> 0.91666667

Sheet human_alignment_by_indicator
A1: run_type | B1: run_no | C1: model | D1: indicator_id | E1: indicator_name | F1: human_validated_rows | G1: human_agreements | H1: human_disagreements | I1: human_alignment_rate
A2: main | B2: 1 | C2: CLAUDE | D2: R01 | E2: Freely given consent | F2: 20 | G2: 19 | H2: 1 | I2: 0.95
A3: main | B3: 1 | C3: CLAUDE | D3: R02 | E3: Right to withdraw | F3: 20 | G3: 20 | H3: 0 | I3: 1
A4: main | B4: 1 | C4: CLAUDE | D4: R03 | E4: Demonstrability of consent | F4: 20 | G4: 20 | H4: 0 | I4: 1
A5: main | B5: 1 | C5: CLAUDE | D5: R04 | E5: Specific consent (granularity) | F5: 20 | G5: 20 | H5: 0 | I5: 1
A6: main | B6: 1 | C6: CLAUDE | D6: R05 | E6: Informed consent | F6: 20 | G6: 20 | H6: 0 | I6: 1
A7: main | B7: 1 | C7: CLAUDE | D7: R06 | E7: Unambiguous indication | F7: 20 | G7: 20 | H7: 0 | I7: 1
A8: main | B8: 1 | C8: CLAUDE | D8: R07 | E8: Identity of controller | F8: 20 | G8: 20 | H8: 0 | I8: 1
A9: main | B9: 1 | C9: CLAUDE | D9: R08 | E9: Contact details | F9: 20 | G9: 20 | H9: 0 | I9: 1
A10: main | B10: 1 | C10: CLAUDE | D10: R09 | E10: Purpose specification | F10: 20 | G10: 20 | H10: 0 | I10: 1
A11: main | B11: 1 | C11: CLAUDE | D11: R10 | E11: Legal basis disclosure | F11: 20 | G11: 20 | H11: 0 | I11: 1
A12: main | B12: 1 | C12: CLAUDE | D12: R11 | E12: Third-party recipients | F12: 20 | G12: 20 | H12: 0 | I12: 1
A13: main | B13: 1 | C13: CLAUDE | D13: R12 | E13: International transfers | F13: 20 | G13: 20 | H13: 0 | I13: 1
... A72: main | B72: 1 | C72: LLAMA | D72: R18 | E72: Layered information / clarity of information | F72: 20 | G72: 20 | H72: 0 | I72: 1

Sheet trustworthiness
A1: run_type | B1: run_no | C1: model | D1: hallucination_rate | E1: groundedness_rate | F1: human_alignment_rate | G1: human_validated_rows | H1: groundedness_pass_gt_90pct | I1: stability_from_repeat_workbook
A2: main | B2: 1 | C2: CLAUDE | D2: 0 | E2: 1 | F2: 0.98333333 | G2: 360 | H2: TRUE
A3: main | B3: 1 | C3: GEMINI | D3: 0.0058651026 | E3: 0.9941349 | F3: 0.93888889 | G3: 360 | H3: TRUE
A4: main | B4: 1 | C4: GPT | D4: 0.031055901 | E4: 0.9689441 | F4: 0.91666667 | G4: 360 | H4: TRUE
A5: main | B5: 1 | C5: LLAMA | D5: 0.0034013605 | E5: 0.99659864 | F5: 0.97058824 | G5: 340 | H5: TRUE

Sheet validation_notes
A1: run_type | B1: run_no | C1: site_name | D1: domain | E1: model | F1: indicator_id | G1: llm_score | H1: human_score | I1: validation_category | J1: validation_category_norm | K1: validation_note | L1: evidence_quote
A2: main | B2: 1 | C2: About You | D2: aboutyou.de | E2: GPT | F2: R01 | G2: 1 | H2: 1 | I2: VC | J2: VC | K2: Minor formatting differences in extracted quote. | L2: In order to offer you a personal user experience, we and our 35 partners need your consent (click on "Ok"). If you do not consent (click "opt-out"), we will limit our use of cookies and technologies to those that are strictly necessary to make our site safe, secure and available in the way you want ("performance") - but we will not be able to provide you with the full ABOUT YOU experience.
A3: main | B3: 1 | C3: About You | D3: aboutyou.de | E3: GPT | F3: R02 | G3: 0 | H3: 0 | I3: VC | J3: VC | K3: Minor formatting differences in extracted quote. | L3: You can adjust your consent individually by clicking on "Settings" and revoke it at any time with effect for the future.
A4: main | B4: 1 | C4: About You | D4: aboutyou.de | E4: GPT | F4: R04 | G4: 1 | H4: 0 | I4: MC | J4: MC | K4: Minor formatting differences in extracted quote. | L4: With your consent, we would like to store and/or retrieve information on your end device (e.g. IP address, user ID, browser information, device identifiers) and use this information for the following purposes: to identify you on third party sites (including using pseudonymised email addresses and phone numbers); to show you personalised ads and content, here and on third party sites ("personalised ads and content"); for ad and content measurement; to better understand you ("market research") and so that we can develop even better products and services for you ("product development").
A5: main | B5: 1 | C5: About You | D5: aboutyou.de | E5: GPT | F5: R06 | G5: 0 | H5: 0 | I5: H | J5: H | K5: Hallucination: fabricated evidence not present in source. | L5: Consent is described as resulting from clicking "Ok" or adjusting settings.
A6: main | B6: 1 | C6: About You | D6: aboutyou.de | E6: GPT | F6: R10 | G6: 0 | H6: 0 | I6: VC | J6: VC | K6: Different but relevant evidence excerpts selected across models. | L6: The legal basis for this processing is your consent (Art. 6 (1) a) GDPR).
A7: main | B7: 1 | C7: About You | D7: aboutyou.de | E7: GPT | F7: R12 | G7: 1 | H7: 0 | I7: MC | J7: MC | K7: Relevant section exists, but model failed to identify it. | L7: NO_EVIDENCE_FOUND
A8: main | B8: 1 | C8: About You | D8: aboutyou.de | E8: GPT | F8: R13 | G8: 0 | H8: 0 | I8: VC | J8: VC | K8: Generic retention wording, but relevant. | L8: The information is stored and automatically deleted after the aforementioned purposes have been achieved. The standard periods for deletion are based on the criterion of necessity.
A9: main | B9: 1 | C9: About You | D9: aboutyou.de | E9: GPT | F9: R14 | G9: 0 | H9: 0 | I9: VC | J9: VC | K9: Evidence spans two paragraphs | L9: In addition to the right to revoke your consent given to us, you are entitled to the following further rights if the respective legal requirements are met: the right of access about your personal data stored by us (Art. 15 GDPR), in particular you can request information about the processing purposes, the categories of personal data, the categories of recipients to whom your data has been or will be disclosed, the planned storage period, the origin of your data, if it has not been collected directly from you.
A10: main | B10: 1 | C10: About You | D10: aboutyou.de | E10: GPT | F10: R17 | G10: 0 | H10: 0 | I10: VC | J10: VC | K10: Best evidence: explicit complaint right and supervisory authority reference. | L10: Both "Reject" and "Ok" buttons are visible on the first layer, with equal size, color (black background with white text), and placement side by side. The "Settings" option is smaller and less prominent but does not replace reject.
A11: main | B11: 1 | C11: About You | D11: aboutyou.de | E11: GPT | F11: R18 | G11: 0 | H11: 0 | I11: VC | J11: VC | K11: same evidence | L11: You can easily jump directly to the section you are interested in by clicking on the respective chapter headings.
A12: main | B12: 1 | C12: Allegro | D12: allegro.pl | E12: GPT | F12: R04 | G12: 1 | H12: 0 | I12: MC | J12: MC | K12: Granular option found by other models. | L12: By giving your consent to the storage of information on your terminal equipment, and to the access and processing of data, including in the sphere of profiling as well as market and statistical analysis, you will easily find exactly what you are searching for and what you need on Allegro.
A13: main | B13: 1 | C13: Allegro | D13: allegro.pl | E13: GPT | F13: R06 | G13: 0 | H13: 0 | I13: H | J13: H | K13: Hallucination: fabricated evidence not present in source. | L13: Consent is described as resulting from explicit actions such as clicking "I agree" or "I do not agree".
... A261: main | B261: 1 | C261: Zooplus | D261: zooplus.de | E261: LLAMA | F261: R03 | G261: 1 | H261: 0 | I261: MC | J261: MC | K261: Relevant evidence exists, but model failed to identify it. | L261: NO_EVIDENCE_FOUND

Sheet stability_detail
A1: site_name | B1: domain | C1: model | D1: indicator_id | E1: 1 | F1: 2 | G1: 3 | H1: stable
A2: About You | B2: aboutyou.de | C2: CLAUDE | D2: R01 | E2: 1 | F2: 1 | G2: 1 | H2: 1
A3: About You | B3: aboutyou.de | C3: CLAUDE | D3: R02 | E3: 0 | F3: 0 | G3: 0 | H3: 1
A4: About You | B4: aboutyou.de | C4: CLAUDE | D4: R03 | E4: 0 | F4: 0 | G4: 0 | H4: 1
A5: About You | B5: aboutyou.de | C5: CLAUDE | D5: R04 | E5: 0 | F5: 0 | G5: 0 | H5: 1
A6: About You | B6: aboutyou.de | C6: CLAUDE | D6: R05 | E6: 0 | F6: 0 | G6: 0 | H6: 1
A7: About You | B7: aboutyou.de | C7: CLAUDE | D7: R06 | E7: 0 | F7: 0 | G7: 0 | H7: 1
A8: About You | B8: aboutyou.de | C8: CLAUDE | D8: R07 | E8: 0 | F8: 0 | G8: 0 | H8: 1
A9: About You | B9: aboutyou.de | C9: CLAUDE | D9: R08 | E9: 0 | F9: 0 | G9: 0 | H9: 1
A10: About You | B10: aboutyou.de | C10: CLAUDE | D10: R09 | E10: 0 | F10: 0 | G10: 0 | H10: 1
A11: About You | B11: aboutyou.de | C11: CLAUDE | D11: R10 | E11: 0 | F11: 0 | G11: 0 | H11: 1
A12: About You | B12: aboutyou.de | C12: CLAUDE | D12: R11 | E12: 0 | F12: 0 | G12: 0 | H12: 1
A13: About You | B13: aboutyou.de | C13: CLAUDE | D13: R12 | E13: 0 | F13: 0 | G13: 0 | H13: 1
... A711: eMAG | B711: emag.ro | C711: LLAMA | D711: R18 | E711: 0 | F711: 0 | G711: 0 | H711: 1

Sheet stability_by_model
A1: model | B1: stable_cases | C1: total_cases | D1: stability_rate
A2: CLAUDE | B2: 180 | C2: 180 | D2: 1
A3: GEMINI | B3: 171 | C3: 180 | D3: 0.95
A4: GPT | B4: 173 | C4: 180 | D4: 0.96111111
A5: LLAMA | B5: 166 | C5: 170 | D5: 0.97647059

Sheet stability_by_indicator
A1: model | B1: indicator_id | C1: stable_cases | D1: total_cases | E1: stability_rate
A2: CLAUDE | B2: R01 | C2: 10 | D2: 10 | E2: 1
A3: CLAUDE | B3: R02 | C3: 10 | D3: 10 | E3: 1
A4: CLAUDE | B4: R03 | C4: 10 | D4: 10 | E4: 1
A5: CLAUDE | B5: R04 | C5: 10 | D5: 10 | E5: 1
A6: CLAUDE | B6: R05 | C6: 10 | D6: 10 | E6: 1
A7: CLAUDE | B7: R06 | C7: 10 | D7: 10 | E7: 1
A8: CLAUDE | B8: R07 | C8: 10 | D8: 10 | E8: 1
A9: CLAUDE | B9: R08 | C9: 10 | D9: 10 | E9: 1
A10: CLAUDE | B10: R09 | C10: 10 | D10: 10 | E10: 1
A11: CLAUDE | B11: R10 | C11: 10 | D11: 10 | E11: 1
A12: CLAUDE | B12: R11 | C12: 10 | D12: 10 | E12: 1
A13: CLAUDE | B13: R12 | C13: 10 | D13: 10 | E13: 1
... A72: LLAMA | B72: R18 | C72: 10 | D72: 10 | E72: 1
